lit_nlp/__init__.py
lit_nlp/app.py
lit_nlp/dev_server.py
lit_nlp/notebook.py
lit_nlp/server_config.py
lit_nlp/server_flags.py
lit_nlp/server_flags_test.py
lit_nlp/api/__init__.py
lit_nlp/api/components.py
lit_nlp/api/dataset.py
lit_nlp/api/dataset_test.py
lit_nlp/api/dtypes.py
lit_nlp/api/layout.py
lit_nlp/api/model.py
lit_nlp/api/model_test.py
lit_nlp/api/types.py
lit_nlp/api/types_test.py
lit_nlp/client/build/default/main.js
lit_nlp/client/build/default/main.js.LICENSE.txt
lit_nlp/client/build/default/main.js.map
lit_nlp/client/build/default/static/favicon.png
lit_nlp/client/build/default/static/index.html
lit_nlp/client/build/default/static/interstitial-select.png
lit_nlp/client/build/default/static/onboarding_1_welcome.gif
lit_nlp/client/build/default/static/onboarding_2_modules.gif
lit_nlp/client/build/default/static/onboarding_3_workspaces.gif
lit_nlp/client/build/default/static/onboarding_4_explore.gif
lit_nlp/client/build/default/static/onboarding_5_toolbars.gif
lit_nlp/client/build/default/static/onboarding_6_compare.gif
lit_nlp/client/build/default/static/onboarding_7_start.gif
lit_nlp/client/build/default/static/potato.svg
lit_nlp/components/__init__.py
lit_nlp/components/ablation_flip.py
lit_nlp/components/ablation_flip_int_test.py
lit_nlp/components/ablation_flip_test.py
lit_nlp/components/annotators.py
lit_nlp/components/backtranslator.py
lit_nlp/components/cf_utils.py
lit_nlp/components/cf_utils_test.py
lit_nlp/components/classification_results.py
lit_nlp/components/classification_results_test.py
lit_nlp/components/core.py
lit_nlp/components/curves.py
lit_nlp/components/curves_test.py
lit_nlp/components/gradient_maps.py
lit_nlp/components/gradient_maps_test.py
lit_nlp/components/hotflip.py
lit_nlp/components/hotflip_int_test.py
lit_nlp/components/hotflip_test.py
lit_nlp/components/image_gradient_maps.py
lit_nlp/components/image_gradient_maps_test.py
lit_nlp/components/index.py
lit_nlp/components/lime_explainer.py
lit_nlp-1.3.1.dist-info/LICENSE
lit_nlp-1.3.1.dist-info/METADATA
lit_nlp-1.3.1.dist-info/WHEEL
lit_nlp-1.3.1.dist-info/top_level.txt
lit_nlp-1.3.1.dist-info/RECORD
