Metadata-Version: 2.1
Name: lit-nlp
Version: 1.3.1
Summary: 🔥LIT: The Learning Interpretability Tool
Author-email: "Google, LLC" <lit-dev@google.com>
License: 
Project-URL: Homepage, https://github.com/pair-code/lit
Project-URL: Repository, https://github.com/PAIR-code/lit
Project-URL: Bug Tracker, https://github.com/PAIR-code/lit/issues
Keywords: interpretability,interpretable artifical intelligence,explainable,explainable artifical intelligence,XAI,computer vision,natural language processing,artifical intelligence,machine learning,deep learning,visualization,visual analytics,tensorflow,tf,torch
Classifier: Development Status :: 5 - Production/Stable
Classifier: Framework :: Jupyter
Classifier: Framework :: Pytest
Classifier: Intended Audience :: Developers
Classifier: Intended Audience :: Science/Research
Classifier: License :: OSI Approved :: Apache Software License
Classifier: Operating System :: OS Independent
Classifier: Programming Language :: JavaScript
Classifier: Programming Language :: Python :: 3 :: Only
Classifier: Programming Language :: Python :: 3.10
Classifier: Topic :: Scientific/Engineering :: Artificial Intelligence
Classifier: Topic :: Scientific/Engineering :: Information Analysis
Classifier: Topic :: Scientific/Engineering :: Visualization
Classifier: Typing :: Typed
Requires-Python: >=3.9
License-File: LICENSE
Requires-Dist: absl-py>=1.4.0
Requires-Dist: annoy>=1.17.3
Requires-Dist: attrs>=22.1.0
Requires-Dist: etils[epath]>=1.5.0
Requires-Dist: filelock>=3.12.3
Requires-Dist: google-cloud-translate>=3.11.1
Requires-Dist: ipython>=7.34.0
Requires-Dist: Levenshtein>=0.21.1
Requires-Dist: matplotlib>=3.7.1
Requires-Dist: ml-collections>=0.1.1
Requires-Dist: numpy<2.0.0,>=1.24.1
Requires-Dist: pandas[output-formatting]>=2.0.3
Requires-Dist: Pillow>=10.0.0
Requires-Dist: portpicker>=1.5.2
Requires-Dist: requests>=2.31.0
Requires-Dist: rouge-score>=0.1.2
Requires-Dist: sacrebleu>=2.3.1
Requires-Dist: saliency>=0.1.3
Requires-Dist: scikit-learn>=1.0.2
Requires-Dist: scipy>=1.10.1
Requires-Dist: shap<0.46.0,>=0.42.0
Requires-Dist: six>=1.16.0
Requires-Dist: termcolor>=2.3.0
Requires-Dist: tqdm>=4.64.0
Requires-Dist: werkzeug>=2.2.3
Provides-Extra: examples-common
Requires-Dist: gunicorn>=20.1.0; extra == "examples-common"
Requires-Dist: tensorflow>=2.16.0; extra == "examples-common"
Requires-Dist: transformers>=4.27.1; extra == "examples-common"
Provides-Extra: examples-discriminative-ai
Requires-Dist: lit-nlp[examples-common]; extra == "examples-discriminative-ai"
Requires-Dist: tensorflow-datasets>=4.9.0; extra == "examples-discriminative-ai"
Requires-Dist: tf-keras>=2.16; extra == "examples-discriminative-ai"
Provides-Extra: examples-generative-ai
Requires-Dist: lit-nlp[examples-common]; extra == "examples-generative-ai"
Requires-Dist: google-cloud-aiplatform>=1.60.0; extra == "examples-generative-ai"
Requires-Dist: keras>=3.0.0; extra == "examples-generative-ai"
Requires-Dist: keras-nlp>=0.14.0; extra == "examples-generative-ai"
Requires-Dist: sentencepiece==0.1.99; extra == "examples-generative-ai"
Requires-Dist: tensorflow-text>=2.16.0; extra == "examples-generative-ai"
Requires-Dist: torch>=2.0.0; extra == "examples-generative-ai"
Requires-Dist: vertexai>=1.49.0; extra == "examples-generative-ai"
Provides-Extra: umap
Requires-Dist: umap-learn==0.5.6; extra == "umap"
Provides-Extra: test
Requires-Dist: lit-nlp[examples-discriminative-ai]; extra == "test"
Requires-Dist: lit-nlp[examples-generative-ai]; extra == "test"
Requires-Dist: lit-nlp[umap]; extra == "test"
Requires-Dist: lime==0.2.0.1; extra == "test"
Requires-Dist: pytest<8.0.0,>=7.4.0; extra == "test"
Requires-Dist: webtest>=2.0; extra == "test"
